<?xml version="1.0" encoding="utf-8"?>
<!DOCTYPE hibernate-mapping PUBLIC "-//Hibernate/Hibernate Mapping DTD 3.0//EN"
"http://hibernate.sourceforge.net/hibernate-mapping-3.0.dtd">
<!-- 
    Mapping file autogenerated by MyEclipse Persistence Tools
-->
<hibernate-mapping>
    <class name="com.domain.Resources" table="resources" catalog="dhulab">
        <id name="id" type="java.lang.Integer">
            <column name="id" />
            <generator class="native" />
        </id>
        <many-to-one name="resourceSubtype" class="com.domain.ResourceSubtype" fetch="select">
            <column name="subtypeid" />
        </many-to-one>
        <many-to-one name="resourceType" class="com.domain.ResourceType" fetch="select">
            <column name="typeid" />
        </many-to-one>
        <many-to-one name="userinfo" class="com.domain.Userinfo" fetch="select">
            <column name="userid" />
        </many-to-one>
        <property name="extendname" type="string">
            <column name="extendname" />
        </property>
        <property name="filename" type="string">
            <column name="filename" />
        </property>
        <property name="storefilename" type="string">
            <column name="storefilename" />
        </property>
        <property name="filesize" type="string">
            <column name="filesize" length="50" />
        </property>
        <property name="uploadtime" type="java.sql.Timestamp">
            <column name="uploadtime" length="19" />
        </property>
        <property name="downloadcounts" type="java.lang.Integer">
            <column name="downloadcounts" />
        </property>
    </class>
</hibernate-mapping>
